webhelpers2/__init__.py
webhelpers2/constants.py
webhelpers2/containers.py
webhelpers2/date.py
webhelpers2/misc.py
webhelpers2/number.py
webhelpers2/text.py
webhelpers2/html/__init__.py
webhelpers2/html/_autolink.py
webhelpers2/html/_literal.py
webhelpers2/html/_render.py
webhelpers2/html/builder.py
webhelpers2/html/tags.py
webhelpers2/html/tools.py
WebHelpers2-2.1.dist-info/LICENSE
WebHelpers2-2.1.dist-info/METADATA
WebHelpers2-2.1.dist-info/WHEEL
WebHelpers2-2.1.dist-info/top_level.txt
WebHelpers2-2.1.dist-info/RECORD
