Metadata-Version: 2.1
Name: WebHelpers2
Version: 2.1
Summary: WebHelpers2
Home-page: https://webhelpers2.readthedocs.org/en/latest/
Author: Mike Orr, Ben Bangert, Phil Jenvey
Author-email: sluggoster@gmail.com, ben@groovie.org, pjenvey@groovie.org
Classifier: Development Status :: 5 - Production/Stable
Classifier: Environment :: Web Environment
Classifier: Framework :: Pylons
Classifier: Framework :: Pyramid
Classifier: Intended Audience :: Developers
Classifier: License :: OSI Approved :: MIT License
Classifier: Programming Language :: Python
Classifier: Topic :: Internet :: WWW/HTTP :: Dynamic Content
Classifier: Topic :: Software Development :: Libraries :: Python Modules
License-File: LICENSE
Requires-Dist: MarkupSafe >=0.9.2
Requires-Dist: six >=1.4.0
